func_argparse/__init__.py
func_argparse/func_argparse_test.py
func_argparse/py.typed
func_argparse-1.1.1.dist-info/LICENSE
func_argparse-1.1.1.dist-info/METADATA
func_argparse-1.1.1.dist-info/WHEEL
func_argparse-1.1.1.dist-info/top_level.txt
func_argparse-1.1.1.dist-info/RECORD
