Metadata-Version: 2.1
Name: func-argparse
Version: 1.1.1
Summary: Generate CLI ArgumentParser from a function signature.
Home-page: https://github.com/gwenzek/func_argparse
Author: gwenzek
License: BSD
Platform: UNKNOWN
Provides-Extra: dev
Requires-Dist: mypy (>=0.730) ; extra == 'dev'
Requires-Dist: pytest ; extra == 'dev'
Requires-Dist: black ; extra == 'dev'
Requires-Dist: isort ; extra == 'dev'
